zipcode_coordinates/__init__.py
zipcode_coordinates/data/DE.py
zipcode_coordinates-20230901.617.dist-info/LICENSE
zipcode_coordinates-20230901.617.dist-info/METADATA
zipcode_coordinates-20230901.617.dist-info/WHEEL
zipcode_coordinates-20230901.617.dist-info/top_level.txt
zipcode_coordinates-20230901.617.dist-info/RECORD
