Metadata-Version: 2.1
Name: zipcode-coordinates
Version: 20230901.617
Summary: Automatically updated map of German zip codes (PLZ) and corresponding geo coordinates.
Author-email: Philipp Bosch <hello@pb.io>
Project-URL: Homepage, https://github.com/selfmade-energy/zipcode-coordinates
Project-URL: Bug Tracker, https://github.com/selfmade-energy/zipcode-coordinates/issues
Classifier: Programming Language :: Python :: 3
Classifier: License :: OSI Approved :: MIT License
Classifier: Operating System :: OS Independent
Requires-Python: >=3.7
License-File: LICENSE
